<annotation verified="yes">
    <folder>Annotation</folder>
    <filename>20170911155030-500_color-%5BROI-1%5D-33.jpg</filename>
    <path>TCC-PascalVOC-export/Annotations/20170911155030-500_color-%5BROI-1%5D-33.jpg</path>
    <source>
        <database>Unknown</database>
    </source>
    <size>
        <width>1920</width>
        <height>582</height>
        <depth>3</depth>
    </size>
    <segmented>0</segmented>
    <object>
    <name>Eixo</name>
    <pose>Unspecified</pose>
    <truncated>0</truncated>
    <difficult>0</difficult>
    <bndbox>
        <xmin>1638.8619014573214</xmin>
        <ymin>460.01473112128144</ymin>
        <xmax>1700.1526717557254</xmax>
        <ymax>526.6051201372998</ymax>
    </bndbox>
</object><object>
    <name>Eixo</name>
    <pose>Unspecified</pose>
    <truncated>0</truncated>
    <difficult>0</difficult>
    <bndbox>
        <xmin>1265.7876474670368</xmin>
        <ymin>458.68292334096105</ymin>
        <xmax>1333.7404580152672</xmax>
        <ymax>529.2687356979404</ymax>
    </bndbox>
</object>
</annotation>
